movado/__init__.py
movado/chained_estimator.py
movado/controller.py
movado/distance_controller.py
movado/estimator.py
movado/hoeffding_adaptive_tree_model.py
movado/kernel_regression_model.py
movado/mab_controller.py
movado/mab_handler.py
movado/mab_handler_cats.py
movado/mab_handler_cb.py
movado/model.py
movado/movado.py
movado/movado_static.py
movado/shadow_controller.py
movado/voting_controller.py
movado-0.7.4.dist-info/LICENSE
movado-0.7.4.dist-info/METADATA
movado-0.7.4.dist-info/WHEEL
movado-0.7.4.dist-info/RECORD
