Metadata-Version: 2.1
Name: movado
Version: 0.7.4
Summary: Approximation utility for expensive fitness functions
Author: Daniele Paletti
Author-email: danielepaletti98@gmail.com
Requires-Python: >=3.9,<4.0
Classifier: Programming Language :: Python :: 3
Classifier: Programming Language :: Python :: 3.9
Classifier: Programming Language :: Python :: 3.10
Classifier: Programming Language :: Python :: 3.11
Requires-Dist: joblib (>=1.0,<2.0)
Requires-Dist: numpy (>=1.19,<2.0)
Requires-Dist: plotly (>=4.14,<5.0)
Requires-Dist: river (==0.14)
Requires-Dist: scikit-learn (>=0.24,<0.25)
Requires-Dist: scipy (>=1.5,<2.0)
Requires-Dist: vowpalwabbit (>=8,<9)
